CHANGELOG.txt
LICENCE.txt
MANIFEST.in
README.txt
setup.py
RiteshAwesomeMLlibraries.egg-info/PKG-INFO
RiteshAwesomeMLlibraries.egg-info/SOURCES.txt
RiteshAwesomeMLlibraries.egg-info/dependency_links.txt
RiteshAwesomeMLlibraries.egg-info/top_level.txt
riamll/__init__.py