Metadata-Version: 1.1
Name: RiteshAwesomeMLlibraries
Version: 0.0.2
Summary: ML Module Collection
Home-page: UNKNOWN
Author: Ritesh Yadav
Author-email: daydreamingguy941@gmail.com
License: MIT
Keywords: Machine Learning
Platform: UNKNOWN
Classifier: Development Status :: 5 - Production/Stable
Classifier: Intended Audience :: Education
Classifier: Operating System :: Microsoft :: Windows :: Windows 10
Classifier: License :: OSI Approved :: MIT License
Classifier: Programming Language :: Python :: 3
